metastock/__init__.py
metastock/__main__.py
metastock/bin/__init__.py
metastock/bin/accessor.py
metastock/bin/analysis/__init__.py
metastock/bin/mbinance_start_consumer.py
metastock/bin/mbinance_trade.py
metastock/bin/start_consumer.py
metastock/bin/test/__init__.py
metastock/bin/test/binance/__init__.py
metastock/bin/test/binance/chart_trade_list.py
metastock/bin/test/binance/dash_test.py
metastock/bin/test/binance/hull.py
metastock/bin/test/binance/mtest.py
metastock/bin/test/binance/read_csv.py
metastock/bin/test/binance/strategy_config_generator.py
metastock/bin/test/cointegration.py
metastock/bin/test/dummy.py
metastock/bin/test/get_history_data.py
metastock/bin/test/historical.py
metastock/bin/test/hulma.py
metastock/bin/test/linreg.py
metastock/bin/test/pd_to_excel.py
metastock/bin/test/predefined_strategy_generator_1.py
metastock/bin/test/predict.py
metastock/bin/test/rick_fullscreen_app.py
metastock/bin/test/rx_test.py
metastock/bin/test/sqzmom.py
metastock/bin/test/strategy_manager.py
metastock/cli/__init__.py
metastock/cli/app.py
metastock/cli/mbinance/__init__.py
metastock/cli/mbinance/application.py
metastock/cli/mbinance/cmd/__init__.py
metastock/cli/mbinance/cmd/exchange_info_search_symbol_cmd.py
metastock/cli/mbinance/cmd/history_init_candlestick_cmd_v2.py
metastock/cli/mbinance/cmd/queue_consumer_start_cmd.py
metastock/cli/mbinance/cmd/trade.py
metastock/cli/mbinance/config/__init__.py
metastock/cli/mbinance/config/queue_config.py
metastock/cli/mbinance/main.py
metastock/cli/pystock.py
metastock/config/__init__.py
metastock/config/app_config.py
metastock/config/queue_config.py
metastock/config/trading_config.py
metastock/fixture/trade/predefined_inputs/accessor/simple_buy_accessor_v1/default.json
metastock/fixture/trade/predefined_inputs/generator/simple_alert_v1.json
metastock/fixture/trade/predefined_inputs/generator/simple_sqz_mom_v1.json
metastock/fixture/trade/predefined_inputs/generator/tick_shark_v1.json
metastock-0.1.3.dist-info/METADATA
metastock-0.1.3.dist-info/WHEEL
metastock-0.1.3.dist-info/entry_points.txt
metastock-0.1.3.dist-info/RECORD
