Metadata-Version: 2.1
Name: metastock
Version: 0.1.3
Summary: 
Author: wsl
Author-email: mr.vjcspy@gmail.com
Requires-Python: >=3.11,<4.0
Classifier: Programming Language :: Python :: 3
Classifier: Programming Language :: Python :: 3.11
Classifier: Programming Language :: Python :: 3.12
Requires-Dist: annotated-types (>=0.5.0,<0.6.0)
Requires-Dist: arrow (>=1.2.3,<2.0.0)
Requires-Dist: attrs (>=23.1.0,<24.0.0)
Requires-Dist: binance-connector (>=3.5.1,<4.0.0)
Requires-Dist: binance-futures-connector (>=4.0.0,<5.0.0)
Requires-Dist: cachetools (>=5.3.2,<6.0.0)
Requires-Dist: certifi (>=2023.7.22,<2024.0.0)
Requires-Dist: charset-normalizer (>=3.2.0,<4.0.0)
Requires-Dist: click (>=8.1.7,<9.0.0)
Requires-Dist: colorama (>=0.4.6,<0.5.0)
Requires-Dist: contourpy (>=1.1.0,<2.0.0)
Requires-Dist: cycler (>=0.11.0,<0.12.0)
Requires-Dist: dash (>=2.14.2,<3.0.0)
Requires-Dist: dependency-injector (>=4.41.0,<5.0.0)
Requires-Dist: flask (>=2.3.3,<3.0.0)
Requires-Dist: flask-cors (>=4.0.0,<5.0.0)
Requires-Dist: flask-restx (>=1.2.0,<2.0.0)
Requires-Dist: fonttools (>=4.42.1,<5.0.0)
Requires-Dist: gunicorn (>=21.2.0,<22.0.0)
Requires-Dist: idna (>=3.4,<4.0)
Requires-Dist: jsonschema (>=4.17.0,<5.0.0)
Requires-Dist: jsonschema-specifications (>=2023.7.1,<2024.0.0)
Requires-Dist: kiwisolver (>=1.4.5,<2.0.0)
Requires-Dist: markdown-it-py (>=3.0.0,<4.0.0)
Requires-Dist: marshmallow (>=3.20.1,<4.0.0)
Requires-Dist: matplotlib (>=3.7.2,<4.0.0)
Requires-Dist: mdurl (>=0.1.2,<0.2.0)
Requires-Dist: mplfinance (>=0.12.10b0,<0.13.0)
Requires-Dist: numpy (>=1.25.2,<2.0.0)
Requires-Dist: packaging (>=23.1,<24.0)
Requires-Dist: pandas (>=2.0.3,<3.0.0)
Requires-Dist: pendulum (>=2.1.2,<3.0.0)
Requires-Dist: pika (>=1.3.2,<2.0.0)
Requires-Dist: pika-stubs (>=0.1.3,<0.2.0)
Requires-Dist: pillow (>=10.0.0,<11.0.0)
Requires-Dist: psycopg[binary,pool] (>=3.1.17,<4.0.0)
Requires-Dist: pydantic (>=2.3.0,<3.0.0)
Requires-Dist: pydantic-core (>=2.6.3,<3.0.0)
Requires-Dist: pygments (>=2.16.1,<3.0.0)
Requires-Dist: pyparsing (>=3,<4)
Requires-Dist: pyrsistent (>=0.20.0,<0.21.0)
Requires-Dist: pytest (>=7.4.0,<8.0.0)
Requires-Dist: python-dateutil (>=2.8.2,<3.0.0)
Requires-Dist: python-dotenv (>=1.0.0,<2.0.0)
Requires-Dist: python-json-logger (>=2.0.7,<3.0.0)
Requires-Dist: pytz (>=2023.3,<2024.0)
Requires-Dist: pytzdata (>=2020.1,<2021.0)
Requires-Dist: reactivex (>=4.0.4,<5.0.0)
Requires-Dist: referencing (>=0.30.2,<0.31.0)
Requires-Dist: requests (>=2.31.0,<3.0.0)
Requires-Dist: rich (>=13.5.2,<14.0.0)
Requires-Dist: rpds-py (>=0.9.2,<0.10.0)
Requires-Dist: shellingham (>=1.5.3,<2.0.0)
Requires-Dist: simplejson (>=3.19.1,<4.0.0)
Requires-Dist: six (>=1.16.0,<2.0.0)
Requires-Dist: splunk-handler (>=3.0.0,<4.0.0)
Requires-Dist: sqlalchemy (>=2.0.25,<3.0.0)
Requires-Dist: termcolor (>=2.3.0,<3.0.0)
Requires-Dist: typer (>=0.9.0,<0.10.0)
Requires-Dist: typing-extensions (>=4.7.1,<5.0.0)
Requires-Dist: tzdata (>=2023.3,<2024.0)
Requires-Dist: urllib3 (>=2.0.4,<3.0.0)
Requires-Dist: xlsxwriter (>=3.2.0,<4.0.0)
